tensorflow_decision_forests-1.11.0.dist-info/RECORD
tensorflow_decision_forests-1.11.0.dist-info/WHEEL
tensorflow_decision_forests-1.11.0.dist-info/top_level.txt
tensorflow_decision_forests-1.11.0.dist-info/METADATA
tensorflow_decision_forests-1.11.0.dist-info/LICENSE
tensorflow_decision_forests/__init__.py
tensorflow_decision_forests/keras/grpc_worker_main
tensorflow_decision_forests/keras/keras_internal.py
tensorflow_decision_forests/keras/wrappers.py
tensorflow_decision_forests/keras/keras_tuner_test.py
tensorflow_decision_forests/keras/test_runner.py
tensorflow_decision_forests/keras/core.py
tensorflow_decision_forests/keras/__init__.py
tensorflow_decision_forests/keras/core_inference.py
tensorflow_decision_forests/keras/wrappers_pre_generated.py
tensorflow_decision_forests/keras/keras_test.py
tensorflow_decision_forests/keras/keras_distributed_test.py
tensorflow_decision_forests/keras/keras_internal_test.py
tensorflow_decision_forests/tensorflow/check_version_test.py
tensorflow_decision_forests/tensorflow/check_version.py
tensorflow_decision_forests/tensorflow/core.py
tensorflow_decision_forests/tensorflow/core_test.py
tensorflow_decision_forests/tensorflow/__init__.py
tensorflow_decision_forests/tensorflow/core_inference.py
tensorflow_decision_forests/tensorflow/cc_logging.py
tensorflow_decision_forests/tensorflow/tf_logging.py
tensorflow_decision_forests/tensorflow/tf1_compatibility.py
tensorflow_decision_forests/tensorflow/ops/__init__.py
tensorflow_decision_forests/tensorflow/ops/inference/api.py
tensorflow_decision_forests/tensorflow/ops/inference/inference.so
tensorflow_decision_forests/tensorflow/ops/inference/tf2_test.py
tensorflow_decision_forests/tensorflow/ops/inference/__init__.py
tensorflow_decision_forests/tensorflow/ops/inference/op_dynamic.py
tensorflow_decision_forests/tensorflow/ops/inference/tf1_test.py
tensorflow_decision_forests/tensorflow/ops/inference/op.py
tensorflow_decision_forests/tensorflow/ops/inference/test_utils.py
tensorflow_decision_forests/tensorflow/ops/training/__init__.py
tensorflow_decision_forests/tensorflow/ops/training/op_test.py
tensorflow_decision_forests/tensorflow/ops/training/op_dynamic.py
