Metadata-Version: 2.1
Name: tensorflow_decision_forests
Version: 1.11.0
Summary: Collection of training and inference decision forest algorithms.
Home-page: https://github.com/tensorflow/decision-forests
Author: Google Inc.
Author-email: decision-forests-contact@google.com
License: Apache 2.0
Project-URL: Bug Tracker, https://github.com/tensorflow/decision-forests/issues
Keywords: tensorflow tensor machine learning decision forests random forest gradient boosted decision trees
Classifier: Intended Audience :: Developers
Classifier: Intended Audience :: Education
Classifier: Intended Audience :: Science/Research
Classifier: License :: OSI Approved :: Apache Software License
Classifier: Programming Language :: Python :: 3
Classifier: Programming Language :: Python :: 3.9
Classifier: Programming Language :: Python :: 3.10
Classifier: Programming Language :: Python :: 3.11
Classifier: Programming Language :: Python :: 3 :: Only
Classifier: Topic :: Scientific/Engineering
Classifier: Topic :: Scientific/Engineering :: Mathematics
Classifier: Topic :: Scientific/Engineering :: Artificial Intelligence
Classifier: Topic :: Software Development
Classifier: Topic :: Software Development :: Libraries
Classifier: Topic :: Software Development :: Libraries :: Python Modules
Requires-Python: >=3.9
License-File: LICENSE
Requires-Dist: numpy
Requires-Dist: pandas
Requires-Dist: tensorflow ==2.18.0
Requires-Dist: six
Requires-Dist: absl-py
Requires-Dist: wheel
Requires-Dist: wurlitzer
Requires-Dist: tf-keras ~=2.17
Requires-Dist: ydf
